extensible_provn/__init__.py
extensible_provn/prov_magics.py
extensible_provn/prov_parser.py
extensible_provn/utils.py
extensible_provn/query/__init__.py
extensible_provn/query/intertwined_prov.py
extensible_provn/query/mutable_prov.py
extensible_provn/query/pattern_machinery.py
extensible_provn/query/prov_dictionary.py
extensible_provn/query/provn.py
extensible_provn/query/querier.py
extensible_provn/query/versioned_prov.py
extensible_provn/resources/.empty.txt
extensible_provn/resources/version.txt
extensible_provn/view/__init__.py
extensible_provn/view/dot.py
extensible_provn/view/intertwined_prov.py
extensible_provn/view/mutable_prov.py
extensible_provn/view/prov_dictionary.py
extensible_provn/view/provn.py
extensible_provn/view/test_provn.py
extensible_provn/view/versioned_prov.py
extensible_provn/view/style/__init__.py
extensible_provn/view/style/blackwhite.py
extensible_provn/view/style/default.py
extensible_provn/view/style/dot.py
extensible_provn/view/style/hide.py
extensible_provn/view/style/nohighlight.py
extensible_provn/view/style/paper.py
extensible_provn/view/style/paper2.py
extensible_provn/view/style/paper3.py
extensible_provn/view/style/provtoolbox.py
extensible_provn/view/style/specific.py
extensible_provn-0.2.1.dist-info/LICENSE.txt
extensible_provn-0.2.1.dist-info/METADATA
extensible_provn-0.2.1.dist-info/RECORD
extensible_provn-0.2.1.dist-info/WHEEL
extensible_provn-0.2.1.dist-info/entry_points.txt
extensible_provn-0.2.1.dist-info/top_level.txt
