Metadata-Version: 2.1
Name: extensible-provn
Version: 0.2.1
Summary: Extensible PROV-N visualizer and querier
Home-page: https://github.com/JoaoFelipe/extensible_provn
Author: ('Joao Pimentel',)
Author-email: joaofelipenp@gmail.com
License: MIT
Keywords: provenance visualization
Platform: UNKNOWN
Classifier: Development Status :: 4 - Beta
Classifier: Intended Audience :: Science/Research
Classifier: Intended Audience :: Developers
Classifier: Topic :: Software Development :: Libraries :: Python Modules
Classifier: Topic :: Scientific/Engineering :: Visualization
Classifier: License :: OSI Approved :: MIT License
Classifier: Programming Language :: Python :: 3.6
Classifier: Programming Language :: Python :: 3.5
Classifier: Programming Language :: Python :: 2.7
Requires-Dist: lark-parser
